pyserveuz/__init__.py
pyserveuz/app.py
pyserveuz/middleware.py
pyserveuz/response.py
pyserveuz-0.1.2.dist-info/METADATA
pyserveuz-0.1.2.dist-info/WHEEL
pyserveuz-0.1.2.dist-info/top_level.txt
pyserveuz-0.1.2.dist-info/RECORD
