Metadata-Version: 2.1
Name: pyserveuz
Version: 0.1.2
Summary: Python Web Framework built for learning purposes
Home-page: https://github.com/me/myproject
Author: Jasur Mavlonov
Author-email: jasurmavloniy24@gmail.com
License: MIT
Platform: UNKNOWN
Classifier: License :: OSI Approved :: MIT License
Classifier: Programming Language :: Python
Classifier: Programming Language :: Python :: 3
Classifier: Programming Language :: Python :: 3.6
Classifier: Programming Language :: Python :: Implementation :: CPython
Classifier: Programming Language :: Python :: Implementation :: PyPy
Requires-Python: >=3.9.0
Requires-Dist: Jinja2==3.1.6
Requires-Dist: parse==1.20.2
Requires-Dist: requests==2.32.5
Requires-Dist: requests-wsgi-adapter==0.4.1
Requires-Dist: WebOb==1.8.9
Requires-Dist: whitenoise==6.11.0
